{"cameraMode":{"drawMode":0,"name":"Shaded","section":"Shading Mode"},"sceneLighting":true,"audioPlay":false,"sceneViewState":{"m_AlwaysRefresh":false,"showFog":true,"showSkybox":true,"showFlares":true,"showImageEffects":true,"showParticleSystems":true,"showVisualEffectGraphs":true,"m_FxEnabled":true},"in2DMode":false,"pivot":{"x":2.8045506477355959,"y":0.06528806686401367,"z":2.186992645263672},"rotation":{"x":-0.001651960308663547,"y":0.8464561104774475,"z":-0.5324558615684509,"w":-0.0026254886761307718},"size":2.8525733947753908,"orthographic":false}